{
  "data": {
    "article": {},
    "attachments": {},
    "author_id": "1887391023976038400",
    "conversation_id": "2073957663633821767",
    "created_at": "2026-07-06T03:43:49.000Z",
    "edit_controls": {
      "editable_until": "2026-07-06T04:43:49.000Z",
      "edits_remaining": 5,
      "is_edit_eligible": false
    },
    "edit_history_tweet_ids": [
      "2073976184103121182"
    ],
    "entities": {
      "mentions": [
        {
          "end": 15,
          "id": "1845076547197353984",
          "start": 0,
          "username": "jutangxiao1229"
        }
      ]
    },
    "geo": {},
    "id": "2073976184103121182",
    "in_reply_to_user_id": "1845076547197353984",
    "lang": "zh",
    "note_tweet": {
      "entities": {}
    },
    "possibly_sensitive": false,
    "public_metrics": {
      "bookmark_count": 0,
      "impression_count": 0,
      "like_count": 0,
      "quote_count": 0,
      "reply_count": 0,
      "retweet_count": 0
    },
    "referenced_tweets": [
      {
        "id": "2073971526618263557",
        "type": "replied_to"
      }
    ],
    "reply_settings": "everyone",
    "text": "@jutangxiao1229 专硕也是专😡"
  },
  "includes": {
    "tweets": [
      {
        "article": {},
        "attachments": {},
        "author_id": "1887391023976038400",
        "conversation_id": "2073957663633821767",
        "created_at": "2026-07-06T03:43:49.000Z",
        "edit_controls": {
          "editable_until": "2026-07-06T04:43:49.000Z",
          "edits_remaining": 5,
          "is_edit_eligible": false
        },
        "edit_history_tweet_ids": [
          "2073976184103121182"
        ],
        "entities": {
          "mentions": [
            {
              "end": 15,
              "id": "1845076547197353984",
              "start": 0,
              "username": "jutangxiao1229"
            }
          ]
        },
        "geo": {},
        "id": "2073976184103121182",
        "in_reply_to_user_id": "1845076547197353984",
        "lang": "zh",
        "note_tweet": {
          "entities": {}
        },
        "possibly_sensitive": false,
        "public_metrics": {
          "bookmark_count": 0,
          "impression_count": 0,
          "like_count": 0,
          "quote_count": 0,
          "reply_count": 0,
          "retweet_count": 0
        },
        "referenced_tweets": [
          {
            "id": "2073971526618263557",
            "type": "replied_to"
          }
        ],
        "reply_settings": "everyone",
        "text": "@jutangxiao1229 专硕也是专😡"
      },
      {
        "article": {},
        "attachments": {},
        "author_id": "1845076547197353984",
        "conversation_id": "2073957663633821767",
        "created_at": "2026-07-06T03:25:19.000Z",
        "edit_controls": {
          "editable_until": "2026-07-06T04:25:19.000Z",
          "edits_remaining": 5,
          "is_edit_eligible": false
        },
        "edit_history_tweet_ids": [
          "2073971526618263557"
        ],
        "entities": {
          "mentions": [
            {
              "end": 10,
              "id": "1887391023976038400",
              "start": 0,
              "username": "xiey57828"
            }
          ]
        },
        "geo": {},
        "id": "2073971526618263557",
        "in_reply_to_user_id": "1887391023976038400",
        "lang": "zh",
        "note_tweet": {
          "entities": {}
        },
        "possibly_sensitive": false,
        "public_metrics": {
          "bookmark_count": 0,
          "impression_count": 4,
          "like_count": 1,
          "quote_count": 0,
          "reply_count": 1,
          "retweet_count": 0
        },
        "referenced_tweets": [
          {
            "id": "2073957663633821767",
            "type": "replied_to"
          }
        ],
        "reply_settings": "everyone",
        "text": "@xiey57828 专硕怎么你了😭😭😭"
      }
    ],
    "users": [
      {
        "created_at": "2025-02-06T06:41:19.000Z",
        "description": "🍑MtF大证含糖\n🍥hrt4年，手术无望，已转跨÷\n❤️五好良跨不🚬不🍺不💊不🔪不🔞\n🎂2004老东西\n🏥精神状态超好！？\n😇双相，视力残疾\n🥺ISFJ /INFJ\n🐱所有的一切我都可以释怀，唯独性别…",
        "entities": {
          "url": {
            "urls": [
              {
                "display_url": "ngl.link/xiey57828",
                "end": 23,
                "expanded_url": "https://ngl.link/xiey57828",
                "start": 0,
                "url": "https://t.co/dlkZFZjfgW"
              }
            ]
          }
        },
        "id": "1887391023976038400",
        "location": "佛山市南海区",
        "name": "沐桃",
        "pinned_tweet_id": "2073392144115761597",
        "profile_image_url": "https://pbs.twimg.com/profile_images/2064234686868791296/okgBiTiX_normal.jpg",
        "protected": false,
        "public_metrics": {
          "followers_count": 1216,
          "following_count": 525,
          "like_count": 10334,
          "listed_count": 4,
          "media_count": 223,
          "tweet_count": 4089
        },
        "url": "https://t.co/dlkZFZjfgW",
        "username": "xiey57828",
        "verified": true
      },
      {
        "created_at": "2024-10-12T12:18:34.000Z",
        "description": "含血腥负能量请不要看/infp/含糖2026.03.01/汉语🉑英语🉑日语🉑/小透明/胆小鬼/药学小小只/存在主义/可以来找我聊天但是回复很慢/当日记随时删/监护员暂无",
        "entities": {
          "url": {
            "urls": [
              {
                "display_url": "ngl.link/jutangxiao",
                "end": 23,
                "expanded_url": "https://ngl.link/jutangxiao",
                "start": 0,
                "url": "https://t.co/DUSIG2aP97"
              }
            ]
          }
        },
        "id": "1845076547197353984",
        "location": "🌑 The Moon 🌑",
        "name": "棠",
        "profile_image_url": "https://pbs.twimg.com/profile_images/2046809986580541440/7LXsKC60_normal.jpg",
        "protected": false,
        "public_metrics": {
          "followers_count": 356,
          "following_count": 206,
          "like_count": 5229,
          "listed_count": 0,
          "media_count": 54,
          "tweet_count": 501
        },
        "url": "https://t.co/DUSIG2aP97",
        "username": "jutangxiao1229",
        "verified": true
      }
    ]
  }
}