{
  "data": {
    "article": {},
    "attachments": {},
    "author_id": "1887391023976038400",
    "conversation_id": "2076958289955627212",
    "created_at": "2026-07-14T09:16:24.000Z",
    "edit_controls": {
      "editable_until": "2026-07-14T10:16:24.000Z",
      "edits_remaining": 5,
      "is_edit_eligible": false
    },
    "edit_history_tweet_ids": [
      "2076958983211147723"
    ],
    "entities": {
      "mentions": [
        {
          "end": 13,
          "id": "1153430387504373764",
          "start": 0,
          "username": "xiangcai_nya"
        }
      ]
    },
    "geo": {},
    "id": "2076958983211147723",
    "in_reply_to_user_id": "1153430387504373764",
    "lang": "zh",
    "note_tweet": {
      "entities": {}
    },
    "possibly_sensitive": false,
    "public_metrics": {
      "bookmark_count": 0,
      "impression_count": 0,
      "like_count": 1,
      "quote_count": 0,
      "reply_count": 0,
      "retweet_count": 0
    },
    "referenced_tweets": [
      {
        "id": "2076958289955627212",
        "type": "replied_to"
      }
    ],
    "reply_settings": "everyone",
    "text": "@xiangcai_nya 谈恋爱"
  },
  "includes": {
    "tweets": [
      {
        "article": {},
        "attachments": {},
        "author_id": "1887391023976038400",
        "conversation_id": "2076958289955627212",
        "created_at": "2026-07-14T09:16:24.000Z",
        "edit_controls": {
          "editable_until": "2026-07-14T10:16:24.000Z",
          "edits_remaining": 5,
          "is_edit_eligible": false
        },
        "edit_history_tweet_ids": [
          "2076958983211147723"
        ],
        "entities": {
          "mentions": [
            {
              "end": 13,
              "id": "1153430387504373764",
              "start": 0,
              "username": "xiangcai_nya"
            }
          ]
        },
        "geo": {},
        "id": "2076958983211147723",
        "in_reply_to_user_id": "1153430387504373764",
        "lang": "zh",
        "note_tweet": {
          "entities": {}
        },
        "possibly_sensitive": false,
        "public_metrics": {
          "bookmark_count": 0,
          "impression_count": 0,
          "like_count": 1,
          "quote_count": 0,
          "reply_count": 0,
          "retweet_count": 0
        },
        "referenced_tweets": [
          {
            "id": "2076958289955627212",
            "type": "replied_to"
          }
        ],
        "reply_settings": "everyone",
        "text": "@xiangcai_nya 谈恋爱"
      },
      {
        "article": {},
        "attachments": {},
        "author_id": "1153430387504373764",
        "conversation_id": "2076958289955627212",
        "created_at": "2026-07-14T09:13:39.000Z",
        "edit_controls": {
          "editable_until": "2026-07-14T10:13:39.000Z",
          "edits_remaining": 5,
          "is_edit_eligible": true
        },
        "edit_history_tweet_ids": [
          "2076958289955627212"
        ],
        "entities": {},
        "geo": {},
        "id": "2076958289955627212",
        "lang": "zh",
        "note_tweet": {
          "entities": {}
        },
        "possibly_sensitive": false,
        "public_metrics": {
          "bookmark_count": 0,
          "impression_count": 3,
          "like_count": 2,
          "quote_count": 0,
          "reply_count": 1,
          "retweet_count": 0
        },
        "reply_settings": "everyone",
        "text": "我好无聊\n有没有什么好玩的行为艺术推荐一下我要去做"
      }
    ],
    "users": [
      {
        "created_at": "2025-02-06T06:41:19.000Z",
        "description": "🍑理工男，研0\n🤓gay&反跨\n❤️优秀青年不🚬不🍺不💊不🔪不🔞不键政不跨不女装but视力残疾\n🏥理想主义者&自负\n🥺ISFJ /INFJ\n🐱乐观开朗大男孩，好好生活每一天💪\n亲爱的@ABC13067637",
        "entities": {
          "description": {
            "mentions": [
              {
                "end": 103,
                "start": 91,
                "username": "ABC13067637"
              }
            ]
          },
          "url": {
            "urls": [
              {
                "display_url": "ngl.link/xiey57828",
                "end": 23,
                "expanded_url": "https://ngl.link/xiey57828",
                "start": 0,
                "url": "https://t.co/dlkZFZjfgW"
              }
            ]
          }
        },
        "id": "1887391023976038400",
        "location": "太平间天国",
        "name": "沐桃",
        "pinned_tweet_id": "2076649005967438161",
        "profile_image_url": "https://pbs.twimg.com/profile_images/2064234686868791296/okgBiTiX_normal.jpg",
        "protected": false,
        "public_metrics": {
          "followers_count": 1301,
          "following_count": 525,
          "like_count": 11386,
          "listed_count": 4,
          "media_count": 240,
          "tweet_count": 4437
        },
        "url": "https://t.co/dlkZFZjfgW",
        "username": "xiey57828",
        "verified": true
      },
      {
        "created_at": "2019-07-22T22:23:28.000Z",
        "description": "mtf→mtx(ing)\n想要互fo",
        "id": "1153430387504373764",
        "location": "Archangel, Russia",
        "name": "꧁ 葱花香菜重度依赖 ꧂🍥",
        "pinned_tweet_id": "2074084255555268761",
        "profile_image_url": "https://pbs.twimg.com/profile_images/2073611435129868288/Wr4hsJiq_normal.jpg",
        "protected": false,
        "public_metrics": {
          "followers_count": 534,
          "following_count": 367,
          "like_count": 361,
          "listed_count": 1,
          "media_count": 46,
          "tweet_count": 917
        },
        "url": "",
        "username": "xiangcai_nya",
        "verified": true
      }
    ]
  }
}