{
  "data": {
    "article": {},
    "attachments": {},
    "author_id": "1887391023976038400",
    "conversation_id": "2042952706009313572",
    "created_at": "2026-04-12T00:31:43.000Z",
    "edit_controls": {
      "editable_until": "2026-04-12T01:31:43.000Z",
      "edits_remaining": 5,
      "is_edit_eligible": false
    },
    "edit_history_tweet_ids": [
      "2043124870310228359"
    ],
    "entities": {
      "mentions": [
        {
          "end": 15,
          "id": "1810873766119100416",
          "start": 0,
          "username": "RainBuild_2024"
        },
        {
          "end": 31,
          "id": "1760113409167949824",
          "start": 16,
          "username": "RainEngine2026"
        }
      ]
    },
    "geo": {},
    "id": "2043124870310228359",
    "in_reply_to_user_id": "1810873766119100416",
    "lang": "zh",
    "note_tweet": {
      "entities": {}
    },
    "possibly_sensitive": false,
    "public_metrics": {
      "bookmark_count": 0,
      "impression_count": 0,
      "like_count": 0,
      "quote_count": 0,
      "reply_count": 0,
      "retweet_count": 0
    },
    "referenced_tweets": [
      {
        "id": "2042972067973501312",
        "type": "replied_to"
      }
    ],
    "reply_settings": "everyone",
    "text": "@RainBuild_2024 @RainEngine2026 我也差点不认识你了😡"
  },
  "includes": {
    "tweets": [
      {
        "article": {},
        "attachments": {},
        "author_id": "1887391023976038400",
        "conversation_id": "2042952706009313572",
        "created_at": "2026-04-12T00:31:43.000Z",
        "edit_controls": {
          "editable_until": "2026-04-12T01:31:43.000Z",
          "edits_remaining": 5,
          "is_edit_eligible": false
        },
        "edit_history_tweet_ids": [
          "2043124870310228359"
        ],
        "entities": {
          "mentions": [
            {
              "end": 15,
              "id": "1810873766119100416",
              "start": 0,
              "username": "RainBuild_2024"
            },
            {
              "end": 31,
              "id": "1760113409167949824",
              "start": 16,
              "username": "RainEngine2026"
            }
          ]
        },
        "geo": {},
        "id": "2043124870310228359",
        "in_reply_to_user_id": "1810873766119100416",
        "lang": "zh",
        "note_tweet": {
          "entities": {}
        },
        "possibly_sensitive": false,
        "public_metrics": {
          "bookmark_count": 0,
          "impression_count": 0,
          "like_count": 0,
          "quote_count": 0,
          "reply_count": 0,
          "retweet_count": 0
        },
        "referenced_tweets": [
          {
            "id": "2042972067973501312",
            "type": "replied_to"
          }
        ],
        "reply_settings": "everyone",
        "text": "@RainBuild_2024 @RainEngine2026 我也差点不认识你了😡"
      },
      {
        "article": {},
        "attachments": {},
        "author_id": "1810873766119100416",
        "conversation_id": "2042952706009313572",
        "created_at": "2026-04-11T14:24:32.000Z",
        "edit_controls": {
          "editable_until": "2026-04-11T15:24:32.000Z",
          "edits_remaining": 5,
          "is_edit_eligible": false
        },
        "edit_history_tweet_ids": [
          "2042972067973501312"
        ],
        "entities": {
          "mentions": [
            {
              "end": 15,
              "id": "1760113409167949824",
              "start": 0,
              "username": "RainEngine2026"
            }
          ]
        },
        "geo": {},
        "id": "2042972067973501312",
        "in_reply_to_user_id": "1760113409167949824",
        "lang": "zh",
        "note_tweet": {
          "entities": {}
        },
        "possibly_sensitive": false,
        "public_metrics": {
          "bookmark_count": 0,
          "impression_count": 51,
          "like_count": 2,
          "quote_count": 0,
          "reply_count": 1,
          "retweet_count": 0
        },
        "referenced_tweets": [
          {
            "id": "2042952706009313572",
            "type": "replied_to"
          }
        ],
        "reply_settings": "everyone",
        "text": "@RainEngine2026 差点不认识你了"
      }
    ],
    "users": [
      {
        "created_at": "2025-02-06T06:41:19.000Z",
        "description": "我不是救世主我也不会成为帮凶丨MtF＆友跨🏳️‍⚧️丨大四牲 成绩倒数 想休学丨hrt2024.02.17丨深柜＆期待炸柜？丨INFP 9w1丨爱好散步和MC丨不pass丨梦想srs丨精神状态不好正常吃药不o，我想学Python。https://t.co/ukTVcAQw7k",
        "entities": {
          "description": {
            "urls": [
              {
                "display_url": "t.me/xiey57828",
                "end": 138,
                "expanded_url": "https://t.me/xiey57828",
                "start": 115,
                "url": "https://t.co/ukTVcAQw7k"
              }
            ]
          },
          "url": {
            "urls": [
              {
                "display_url": "ngl.link/xiey57828",
                "end": 23,
                "expanded_url": "https://ngl.link/xiey57828",
                "start": 0,
                "url": "https://t.co/dlkZFZjfgW"
              }
            ]
          }
        },
        "id": "1887391023976038400",
        "location": "宿舍",
        "name": "沐桃🍥",
        "pinned_tweet_id": "2042381887642222758",
        "profile_image_url": "https://pbs.twimg.com/profile_images/2038038302096490496/YzWyl6gU_normal.jpg",
        "protected": false,
        "public_metrics": {
          "followers_count": 348,
          "following_count": 455,
          "like_count": 1647,
          "listed_count": 0,
          "media_count": 35,
          "tweet_count": 601
        },
        "url": "https://t.co/dlkZFZjfgW",
        "username": "xiey57828",
        "verified": false
      },
      {
        "created_at": "2024-07-10T03:08:51.000Z",
        "description": "RainEngine联合创始人/曾小米项目部运营/SimpleUX维护者/喜欢摄影/喜欢折腾各类的Android手机/偶尔发些日常/GMT+8/PM前请征得同意否则Ban/喜欢的事就要做到极致",
        "id": "1810873766119100416",
        "name": "晴日向_Official",
        "pinned_tweet_id": "2036689318245531849",
        "profile_image_url": "https://pbs.twimg.com/profile_images/2042977093999570944/b0OIdVg__normal.jpg",
        "protected": false,
        "public_metrics": {
          "followers_count": 9510,
          "following_count": 907,
          "like_count": 74083,
          "listed_count": 18,
          "media_count": 1480,
          "tweet_count": 10513
        },
        "username": "RainBuild_2024",
        "verified": true
      },
      {
        "created_at": "2024-02-21T01:25:31.000Z",
        "description": "17y/AuDHD/cuteMtF\n普通国内高中生，精神状态还好？，大量隐属\nNo 见证/NSFW\nCN/EN ok\nPM/CS beginner\nGoal :=Coq/?\nGame:我能玩吗\nLover:Exist\n欢迎聊有趣/专业话题\n---\n我们害怕死亡，害怕被扼杀，害怕被唾弃，我们不相信上帝，但我们是相信光明的",
        "id": "1760113409167949824",
        "location": "void data sea",
        "name": "v01d",
        "pinned_tweet_id": "2042615937325764621",
        "profile_image_url": "https://pbs.twimg.com/profile_images/2042946030464045059/F6D8JGmP_normal.jpg",
        "protected": false,
        "public_metrics": {
          "followers_count": 86,
          "following_count": 218,
          "like_count": 2414,
          "listed_count": 0,
          "media_count": 1,
          "tweet_count": 158
        },
        "username": "RainEngine2026",
        "verified": false
      }
    ]
  }
}