{
  "data": {
    "article": {},
    "attachments": {},
    "author_id": "1887391023976038400",
    "conversation_id": "2072881851337941463",
    "created_at": "2026-07-03T08:29:47.000Z",
    "edit_controls": {
      "editable_until": "2026-07-03T09:29:47.000Z",
      "edits_remaining": 5,
      "is_edit_eligible": false
    },
    "edit_history_tweet_ids": [
      "2072960987326779636"
    ],
    "entities": {
      "mentions": [
        {
          "end": 13,
          "id": "1153430387504373764",
          "start": 0,
          "username": "xiangcai_nya"
        },
        {
          "end": 26,
          "id": "1486225700793495552",
          "start": 14,
          "username": "ABC13067637"
        }
      ]
    },
    "geo": {},
    "id": "2072960987326779636",
    "in_reply_to_user_id": "1153430387504373764",
    "lang": "zh",
    "note_tweet": {
      "entities": {}
    },
    "possibly_sensitive": false,
    "public_metrics": {
      "bookmark_count": 0,
      "impression_count": 0,
      "like_count": 0,
      "quote_count": 0,
      "reply_count": 0,
      "retweet_count": 0
    },
    "referenced_tweets": [
      {
        "id": "2072956119803388257",
        "type": "replied_to"
      }
    ],
    "reply_settings": "everyone",
    "text": "@xiangcai_nya @ABC13067637 жҲ‘д»¬жңүдёӨдёӘдәәдҪ жӢҝд»Җд№Ҳе’ҢжҲ‘д»¬жӢјрҹӨ“"
  },
  "includes": {
    "tweets": [
      {
        "article": {},
        "attachments": {},
        "author_id": "1887391023976038400",
        "conversation_id": "2072881851337941463",
        "created_at": "2026-07-03T08:29:47.000Z",
        "edit_controls": {
          "editable_until": "2026-07-03T09:29:47.000Z",
          "edits_remaining": 5,
          "is_edit_eligible": false
        },
        "edit_history_tweet_ids": [
          "2072960987326779636"
        ],
        "entities": {
          "mentions": [
            {
              "end": 13,
              "id": "1153430387504373764",
              "start": 0,
              "username": "xiangcai_nya"
            },
            {
              "end": 26,
              "id": "1486225700793495552",
              "start": 14,
              "username": "ABC13067637"
            }
          ]
        },
        "geo": {},
        "id": "2072960987326779636",
        "in_reply_to_user_id": "1153430387504373764",
        "lang": "zh",
        "note_tweet": {
          "entities": {}
        },
        "possibly_sensitive": false,
        "public_metrics": {
          "bookmark_count": 0,
          "impression_count": 0,
          "like_count": 0,
          "quote_count": 0,
          "reply_count": 0,
          "retweet_count": 0
        },
        "referenced_tweets": [
          {
            "id": "2072956119803388257",
            "type": "replied_to"
          }
        ],
        "reply_settings": "everyone",
        "text": "@xiangcai_nya @ABC13067637 жҲ‘д»¬жңүдёӨдёӘдәәдҪ жӢҝд»Җд№Ҳе’ҢжҲ‘д»¬жӢјрҹӨ“"
      },
      {
        "article": {},
        "attachments": {},
        "author_id": "1153430387504373764",
        "conversation_id": "2072881851337941463",
        "created_at": "2026-07-03T08:10:27.000Z",
        "edit_controls": {
          "editable_until": "2026-07-03T09:10:27.000Z",
          "edits_remaining": 5,
          "is_edit_eligible": false
        },
        "edit_history_tweet_ids": [
          "2072956119803388257"
        ],
        "entities": {
          "mentions": [
            {
              "end": 12,
              "id": "1486225700793495552",
              "start": 0,
              "username": "ABC13067637"
            },
            {
              "end": 23,
              "id": "1887391023976038400",
              "start": 13,
              "username": "xiey57828"
            }
          ]
        },
        "geo": {},
        "id": "2072956119803388257",
        "in_reply_to_user_id": "1486225700793495552",
        "lang": "zh",
        "note_tweet": {
          "entities": {}
        },
        "possibly_sensitive": false,
        "public_metrics": {
          "bookmark_count": 0,
          "impression_count": 6,
          "like_count": 2,
          "quote_count": 0,
          "reply_count": 1,
          "retweet_count": 0
        },
        "referenced_tweets": [
          {
            "id": "2072917470789398634",
            "type": "replied_to"
          }
        ],
        "reply_settings": "everyone",
        "text": "@ABC13067637 @xiey57828 жҲ‘и·ҹдҪ д»¬иҝҷдәӣxqlжӢјдәҶ"
      }
    ],
    "users": [
      {
        "created_at": "2025-02-06T06:41:19.000Z",
        "description": "рҹҚ‘MtFеӨ§иҜҒеҗ«зі–\nрҹҚҘhrt4е№ҙпјҢжүӢжңҜж— жңӣпјҢе·ІиҪ¬и·ЁГ·\nвқӨпёҸдә”еҘҪиүҜи·ЁдёҚрҹҡ¬дёҚрҹҚәдёҚрҹ’ҠдёҚрҹ”ӘдёҚрҹ”һ\nрҹҺӮ2004иҖҒдёңиҘҝ\nрҹҸҘзІҫзҘһзҠ¶жҖҒи¶…еҘҪпјҒпјҹ\nрҹҳҮеҸҢзӣёпјҢи§ҶеҠӣж®Ӣз–ҫ\nрҹҘәISFJ /INFJ\nрҹҗұжүҖжңүзҡ„дёҖеҲҮжҲ‘йғҪеҸҜд»ҘйҮҠжҖҖпјҢе”ҜзӢ¬жҖ§еҲ«вҖҰ",
        "entities": {
          "url": {
            "urls": [
              {
                "display_url": "ngl.link/xiey57828",
                "end": 23,
                "expanded_url": "https://ngl.link/xiey57828",
                "start": 0,
                "url": "https://t.co/dlkZFZjfgW"
              }
            ]
          }
        },
        "id": "1887391023976038400",
        "location": "дҪӣеұұеёӮеҚ—жө·еҢә",
        "name": "жІҗжЎғ",
        "pinned_tweet_id": "2072488261315149858",
        "profile_image_url": "https://pbs.twimg.com/profile_images/2064234686868791296/okgBiTiX_normal.jpg",
        "protected": false,
        "public_metrics": {
          "followers_count": 1176,
          "following_count": 511,
          "like_count": 10103,
          "listed_count": 4,
          "media_count": 217,
          "tweet_count": 4000
        },
        "url": "https://t.co/dlkZFZjfgW",
        "username": "xiey57828",
        "verified": true
      },
      {
        "created_at": "2019-07-22T22:23:28.000Z",
        "description": "mtfвҶ’mtx(ing)\nжғіиҰҒдә’fo",
        "id": "1153430387504373764",
        "location": "Archangel, Russia",
        "name": "к§Ғ и‘ұиҠұйҰҷиҸңйҮҚеәҰдҫқиө– к§ӮрҹҚҘ",
        "profile_image_url": "https://pbs.twimg.com/profile_images/2067242056930746368/6sGN2gJa_normal.jpg",
        "protected": false,
        "public_metrics": {
          "followers_count": 407,
          "following_count": 289,
          "like_count": 175,
          "listed_count": 1,
          "media_count": 21,
          "tweet_count": 468
        },
        "url": "",
        "username": "xiangcai_nya",
        "verified": true
      },
      {
        "created_at": "2022-01-26T06:33:27.000Z",
        "description": "рҹҸіпёҸвҖҚвҡ§пёҸ|INFP | иҪҜд»¶ејҖеҸ‘пҪңе–ңж¬ўеҸҜзҲұзҡ„дёңиҘҝпҪңеҗҢзұ»дә’fo е–ө",
        "id": "1486225700793495552",
        "name": "Mizukiй…ұрҹҚҘ",
        "pinned_tweet_id": "2070438545823826325",
        "profile_image_url": "https://pbs.twimg.com/profile_images/1486227103024844803/BTrXNcAx_normal.jpg",
        "protected": false,
        "public_metrics": {
          "followers_count": 1367,
          "following_count": 587,
          "like_count": 3705,
          "listed_count": 3,
          "media_count": 72,
          "tweet_count": 1644
        },
        "url": "",
        "username": "ABC13067637",
        "verified": false
      }
    ]
  }
}