{
  "data": {
    "article": {},
    "attachments": {},
    "author_id": "1887391023976038400",
    "conversation_id": "2052908153021612429",
    "created_at": "2026-05-09T01:07:45.000Z",
    "edit_controls": {
      "editable_until": "2026-05-09T02:07:45.000Z",
      "edits_remaining": 5,
      "is_edit_eligible": false
    },
    "edit_history_tweet_ids": [
      "2052918411504820262"
    ],
    "entities": {},
    "geo": {},
    "id": "2052918411504820262",
    "in_reply_to_user_id": "1887391023976038400",
    "lang": "qst",
    "note_tweet": {
      "entities": {}
    },
    "possibly_sensitive": false,
    "public_metrics": {
      "bookmark_count": 0,
      "impression_count": 0,
      "like_count": 0,
      "quote_count": 0,
      "reply_count": 0,
      "retweet_count": 0
    },
    "referenced_tweets": [
      {
        "id": "2052908153021612429",
        "type": "replied_to"
      }
    ],
    "reply_settings": "everyone",
    "text": "？？？"
  },
  "includes": {
    "tweets": [
      {
        "article": {},
        "attachments": {},
        "author_id": "1887391023976038400",
        "conversation_id": "2052908153021612429",
        "created_at": "2026-05-09T01:07:45.000Z",
        "edit_controls": {
          "editable_until": "2026-05-09T02:07:45.000Z",
          "edits_remaining": 5,
          "is_edit_eligible": false
        },
        "edit_history_tweet_ids": [
          "2052918411504820262"
        ],
        "entities": {},
        "geo": {},
        "id": "2052918411504820262",
        "in_reply_to_user_id": "1887391023976038400",
        "lang": "qst",
        "note_tweet": {
          "entities": {}
        },
        "possibly_sensitive": false,
        "public_metrics": {
          "bookmark_count": 0,
          "impression_count": 0,
          "like_count": 0,
          "quote_count": 0,
          "reply_count": 0,
          "retweet_count": 0
        },
        "referenced_tweets": [
          {
            "id": "2052908153021612429",
            "type": "replied_to"
          }
        ],
        "reply_settings": "everyone",
        "text": "？？？"
      },
      {
        "article": {},
        "attachments": {},
        "author_id": "1887391023976038400",
        "conversation_id": "2052908153021612429",
        "created_at": "2026-05-09T00:26:59.000Z",
        "edit_controls": {
          "editable_until": "2026-05-09T01:26:59.000Z",
          "edits_remaining": 5,
          "is_edit_eligible": false
        },
        "edit_history_tweet_ids": [
          "2052908153021612429"
        ],
        "entities": {
          "mentions": [
            {
              "end": 24,
              "id": "1946799807366082560",
              "start": 14,
              "username": "LeavesMao"
            }
          ]
        },
        "geo": {},
        "id": "2052908153021612429",
        "lang": "zh",
        "note_tweet": {
          "entities": {}
        },
        "possibly_sensitive": false,
        "public_metrics": {
          "bookmark_count": 0,
          "impression_count": 52,
          "like_count": 7,
          "quote_count": 2,
          "reply_count": 3,
          "retweet_count": 0
        },
        "reply_settings": "everyone",
        "text": "只有和你一起，我才觉得我是我@LeavesMao"
      }
    ],
    "users": [
      {
        "created_at": "2025-02-06T06:41:19.000Z",
        "description": "我是谁？我也不清楚。\n但是最好的妹妹 @LeavesMao 丨另一个？我@xyu1182202不要喂负面情绪😡",
        "entities": {
          "description": {
            "mentions": [
              {
                "end": 29,
                "start": 19,
                "username": "LeavesMao"
              },
              {
                "end": 47,
                "start": 36,
                "username": "xyu1182202"
              }
            ]
          },
          "url": {
            "urls": [
              {
                "display_url": "ngl.link/xiey57828",
                "end": 23,
                "expanded_url": "https://ngl.link/xiey57828",
                "start": 0,
                "url": "https://t.co/dlkZFZjfgW"
              }
            ]
          }
        },
        "id": "1887391023976038400",
        "location": "猫窝",
        "name": "沐桃🍥",
        "pinned_tweet_id": "2048948188070150603",
        "profile_image_url": "https://pbs.twimg.com/profile_images/2051554729109737472/u8eZbhQU_normal.jpg",
        "protected": false,
        "public_metrics": {
          "followers_count": 575,
          "following_count": 308,
          "like_count": 5387,
          "listed_count": 2,
          "media_count": 93,
          "tweet_count": 1959
        },
        "url": "https://t.co/dlkZFZjfgW",
        "username": "xiey57828",
        "verified": false
      }
    ]
  }
}