{
  "data": {
    "article": {},
    "attachments": {},
    "author_id": "1887391023976038400",
    "conversation_id": "2072190725001994299",
    "created_at": "2026-07-01T05:29:02.000Z",
    "edit_controls": {
      "editable_until": "2026-07-01T06:29:02.000Z",
      "edits_remaining": 5,
      "is_edit_eligible": true
    },
    "edit_history_tweet_ids": [
      "2072190725001994299"
    ],
    "entities": {
      "urls": [
        {
          "display_url": "v.douyin.com/iwogwsAbjQU/",
          "end": 67,
          "expanded_url": "https://v.douyin.com/iwogwsAbjQU/",
          "start": 44,
          "status": 200,
          "unwound_url": "https://www.douyin.com/video/7642004059301481754",
          "url": "https://t.co/KaRd85RKHE"
        }
      ]
    },
    "geo": {},
    "id": "2072190725001994299",
    "lang": "zh",
    "note_tweet": {
      "entities": {}
    },
    "possibly_sensitive": false,
    "public_metrics": {
      "bookmark_count": 0,
      "impression_count": 0,
      "like_count": 0,
      "quote_count": 0,
      "reply_count": 0,
      "retweet_count": 0
    },
    "reply_settings": "everyone",
    "text": "樱花下落的速度是秒速五厘米，那么两颗心要多久才能靠近。\n\n游戏叫我的世界，而你是“……”https://t.co/KaRd85RKHE"
  },
  "includes": {
    "tweets": [
      {
        "article": {},
        "attachments": {},
        "author_id": "1887391023976038400",
        "conversation_id": "2072190725001994299",
        "created_at": "2026-07-01T05:29:02.000Z",
        "edit_controls": {
          "editable_until": "2026-07-01T06:29:02.000Z",
          "edits_remaining": 5,
          "is_edit_eligible": true
        },
        "edit_history_tweet_ids": [
          "2072190725001994299"
        ],
        "entities": {
          "urls": [
            {
              "display_url": "v.douyin.com/iwogwsAbjQU/",
              "end": 67,
              "expanded_url": "https://v.douyin.com/iwogwsAbjQU/",
              "start": 44,
              "status": 200,
              "unwound_url": "https://www.douyin.com/video/7642004059301481754",
              "url": "https://t.co/KaRd85RKHE"
            }
          ]
        },
        "geo": {},
        "id": "2072190725001994299",
        "lang": "zh",
        "note_tweet": {
          "entities": {}
        },
        "possibly_sensitive": false,
        "public_metrics": {
          "bookmark_count": 0,
          "impression_count": 0,
          "like_count": 0,
          "quote_count": 0,
          "reply_count": 0,
          "retweet_count": 0
        },
        "reply_settings": "everyone",
        "text": "樱花下落的速度是秒速五厘米，那么两颗心要多久才能靠近。\n\n游戏叫我的世界，而你是“……”https://t.co/KaRd85RKHE"
      }
    ],
    "users": [
      {
        "created_at": "2025-02-06T06:41:19.000Z",
        "description": "🍑MtF大证含糖\n🍥hrt4年，手术无望，已转跨÷\n❤️五好良跨不🚬不🍺不💊不🔪不🔞\n🎂2008刚高考完\n🏥精神状态超好！？\n😇双相，视力残疾\n🥺ISFJ /INFJ\n🐱所有的一切我都可以释怀，唯独性别…",
        "id": "1887391023976038400",
        "location": "佛山市南海区",
        "name": "沐桃",
        "pinned_tweet_id": "2071060255400718346",
        "profile_image_url": "https://pbs.twimg.com/profile_images/2064234686868791296/okgBiTiX_normal.jpg",
        "protected": false,
        "public_metrics": {
          "followers_count": 1130,
          "following_count": 502,
          "like_count": 9848,
          "listed_count": 4,
          "media_count": 206,
          "tweet_count": 3885
        },
        "url": "",
        "username": "xiey57828",
        "verified": false
      }
    ]
  }
}