{
  "data": {
    "article": {},
    "attachments": {
      "media_keys": [
        "3_2073345561055707136"
      ]
    },
    "author_id": "1887391023976038400",
    "context_annotations": [
      {
        "domain": {
          "description": "Categories within Brand Verticals that narrow down the scope of Brands",
          "id": "46",
          "name": "Business Taxonomy"
        },
        "entity": {
          "description": "Brands, companies, advertisers and every non-person handle with the profit intent related to offline and online games such as gaming consoles, tabletop games, video game publishers",
          "id": "1557696940178935808",
          "name": "Gaming Business"
        }
      }
    ],
    "conversation_id": "2073345568987107825",
    "created_at": "2026-07-04T09:57:59.000Z",
    "edit_controls": {
      "editable_until": "2026-07-04T10:57:59.000Z",
      "edits_remaining": 5,
      "is_edit_eligible": true
    },
    "edit_history_tweet_ids": [
      "2073345568987107825"
    ],
    "entities": {
      "urls": [
        {
          "display_url": "pic.x.com/ibOaqtn8pn",
          "end": 36,
          "expanded_url": "https://x.com/xiey57828/status/2073345568987107825/photo/1",
          "media_key": "3_2073345561055707136",
          "start": 13,
          "url": "https://t.co/ibOaqtn8pn"
        }
      ]
    },
    "geo": {},
    "id": "2073345568987107825",
    "lang": "zh",
    "note_tweet": {
      "entities": {}
    },
    "possibly_sensitive": false,
    "public_metrics": {
      "bookmark_count": 0,
      "impression_count": 0,
      "like_count": 0,
      "quote_count": 0,
      "reply_count": 0,
      "retweet_count": 0
    },
    "reply_settings": "everyone",
    "text": "我这双眼睛究竟看了多远！ https://t.co/ibOaqtn8pn"
  },
  "includes": {
    "media": [
      {
        "height": 1079,
        "media_key": "3_2073345561055707136",
        "public_metrics": {},
        "type": "photo",
        "url": "https://pbs.twimg.com/media/HMYAzX9bwAAwwYH.jpg",
        "width": 1919
      }
    ],
    "tweets": [
      {
        "article": {},
        "attachments": {
          "media_keys": [
            "3_2073345561055707136"
          ]
        },
        "author_id": "1887391023976038400",
        "context_annotations": [
          {
            "domain": {
              "description": "Categories within Brand Verticals that narrow down the scope of Brands",
              "id": "46",
              "name": "Business Taxonomy"
            },
            "entity": {
              "description": "Brands, companies, advertisers and every non-person handle with the profit intent related to offline and online games such as gaming consoles, tabletop games, video game publishers",
              "id": "1557696940178935808",
              "name": "Gaming Business"
            }
          }
        ],
        "conversation_id": "2073345568987107825",
        "created_at": "2026-07-04T09:57:59.000Z",
        "edit_controls": {
          "editable_until": "2026-07-04T10:57:59.000Z",
          "edits_remaining": 5,
          "is_edit_eligible": true
        },
        "edit_history_tweet_ids": [
          "2073345568987107825"
        ],
        "entities": {
          "urls": [
            {
              "display_url": "pic.x.com/ibOaqtn8pn",
              "end": 36,
              "expanded_url": "https://x.com/xiey57828/status/2073345568987107825/photo/1",
              "media_key": "3_2073345561055707136",
              "start": 13,
              "url": "https://t.co/ibOaqtn8pn"
            }
          ]
        },
        "geo": {},
        "id": "2073345568987107825",
        "lang": "zh",
        "note_tweet": {
          "entities": {}
        },
        "possibly_sensitive": false,
        "public_metrics": {
          "bookmark_count": 0,
          "impression_count": 0,
          "like_count": 0,
          "quote_count": 0,
          "reply_count": 0,
          "retweet_count": 0
        },
        "reply_settings": "everyone",
        "text": "我这双眼睛究竟看了多远！ https://t.co/ibOaqtn8pn"
      }
    ],
    "users": [
      {
        "created_at": "2025-02-06T06:41:19.000Z",
        "description": "🍑MtF大证含糖\n🍥hrt4年，手术无望，已转跨÷\n❤️五好良跨不🚬不🍺不💊不🔪不🔞\n🎂2004老东西\n🏥精神状态超好！？\n😇双相，视力残疾\n🥺ISFJ /INFJ\n🐱所有的一切我都可以释怀，唯独性别…",
        "entities": {
          "url": {
            "urls": [
              {
                "display_url": "ngl.link/xiey57828",
                "end": 23,
                "expanded_url": "https://ngl.link/xiey57828",
                "start": 0,
                "url": "https://t.co/dlkZFZjfgW"
              }
            ]
          }
        },
        "id": "1887391023976038400",
        "location": "佛山市南海区",
        "name": "沐桃",
        "pinned_tweet_id": "2072883471714783594",
        "profile_image_url": "https://pbs.twimg.com/profile_images/2064234686868791296/okgBiTiX_normal.jpg",
        "protected": false,
        "public_metrics": {
          "followers_count": 1202,
          "following_count": 521,
          "like_count": 10231,
          "listed_count": 4,
          "media_count": 220,
          "tweet_count": 4046
        },
        "url": "https://t.co/dlkZFZjfgW",
        "username": "xiey57828",
        "verified": true
      }
    ]
  }
}