{
  "data": {
    "article": {},
    "attachments": {},
    "author_id": "1887391023976038400",
    "conversation_id": "2059073018253762746",
    "created_at": "2026-05-26T04:11:33.000Z",
    "edit_controls": {
      "editable_until": "2026-05-26T05:11:33.000Z",
      "edits_remaining": 5,
      "is_edit_eligible": false
    },
    "edit_history_tweet_ids": [
      "2059125261548012021"
    ],
    "entities": {
      "mentions": [
        {
          "end": 10,
          "id": "1684572167860801536",
          "start": 0,
          "username": "kukmoon97"
        }
      ]
    },
    "geo": {},
    "id": "2059125261548012021",
    "in_reply_to_user_id": "1684572167860801536",
    "lang": "zh",
    "note_tweet": {
      "entities": {}
    },
    "possibly_sensitive": false,
    "public_metrics": {
      "bookmark_count": 0,
      "impression_count": 0,
      "like_count": 0,
      "quote_count": 0,
      "reply_count": 0,
      "retweet_count": 0
    },
    "referenced_tweets": [
      {
        "id": "2059073018253762746",
        "type": "replied_to"
      }
    ],
    "reply_settings": "everyone",
    "text": "@kukmoon97 一眼求导看单调性再看极值和边界点"
  },
  "includes": {
    "tweets": [
      {
        "article": {},
        "attachments": {},
        "author_id": "1887391023976038400",
        "conversation_id": "2059073018253762746",
        "created_at": "2026-05-26T04:11:33.000Z",
        "edit_controls": {
          "editable_until": "2026-05-26T05:11:33.000Z",
          "edits_remaining": 5,
          "is_edit_eligible": false
        },
        "edit_history_tweet_ids": [
          "2059125261548012021"
        ],
        "entities": {
          "mentions": [
            {
              "end": 10,
              "id": "1684572167860801536",
              "start": 0,
              "username": "kukmoon97"
            }
          ]
        },
        "geo": {},
        "id": "2059125261548012021",
        "in_reply_to_user_id": "1684572167860801536",
        "lang": "zh",
        "note_tweet": {
          "entities": {}
        },
        "possibly_sensitive": false,
        "public_metrics": {
          "bookmark_count": 0,
          "impression_count": 0,
          "like_count": 0,
          "quote_count": 0,
          "reply_count": 0,
          "retweet_count": 0
        },
        "referenced_tweets": [
          {
            "id": "2059073018253762746",
            "type": "replied_to"
          }
        ],
        "reply_settings": "everyone",
        "text": "@kukmoon97 一眼求导看单调性再看极值和边界点"
      },
      {
        "article": {},
        "attachments": {},
        "author_id": "1684572167860801536",
        "conversation_id": "2059073018253762746",
        "created_at": "2026-05-26T00:43:57.000Z",
        "edit_controls": {
          "editable_until": "2026-05-26T01:43:57.000Z",
          "edits_remaining": 5,
          "is_edit_eligible": false
        },
        "edit_history_tweet_ids": [
          "2059073018253762746"
        ],
        "entities": {},
        "geo": {},
        "id": "2059073018253762746",
        "lang": "zh",
        "note_tweet": {
          "entities": {}
        },
        "possibly_sensitive": false,
        "public_metrics": {
          "bookmark_count": 0,
          "impression_count": 581,
          "like_count": 6,
          "quote_count": 0,
          "reply_count": 4,
          "retweet_count": 0
        },
        "reply_settings": "everyone",
        "text": "【考考你】以前我都是出选择题，今天给大家上点强度，出一道证明题：当 0&lt;x&lt;1 时，证明 x-x² &lt; sinx &lt; x"
      }
    ],
    "users": [
      {
        "created_at": "2025-02-06T06:41:19.000Z",
        "description": "MtF🍑08.02.16丨史上最快大证😋2026.5.21无小证😱丨🍥hrt2024.2.17丨除了矮点一无是处😭丨半家长党，努力沟通中😇丨无精神病！🥺丨喜欢@StarryNocts、mc和猫猫叶@LeavesMao🤤丨第二次生命2026.5.16😵。活着才有见到太阳的可能❕丨只发日常碎碎念。",
        "entities": {
          "description": {
            "mentions": [
              {
                "end": 91,
                "start": 79,
                "username": "StarryNocts"
              },
              {
                "end": 108,
                "start": 98,
                "username": "LeavesMao"
              }
            ]
          }
        },
        "id": "1887391023976038400",
        "location": "村里",
        "name": "沐桃",
        "profile_image_url": "https://pbs.twimg.com/profile_images/2055967555228172288/mgsz5OLn_normal.jpg",
        "protected": false,
        "public_metrics": {
          "followers_count": 748,
          "following_count": 348,
          "like_count": 6396,
          "listed_count": 3,
          "media_count": 120,
          "tweet_count": 2369
        },
        "username": "xiey57828",
        "verified": false
      },
      {
        "created_at": "2023-07-27T14:32:20.000Z",
        "description": "🌸 生活在斩杀线之下｜前 #伪娘｜现 #跨性别 女 🌸 Live under kill line ｜ Fmr #crossdresser #CD｜Curr #MtF #transgender #TS 🌸 殺戮ラインの下で生きる｜元 #女装子｜今や #ニューハーフ 🌸",
        "entities": {
          "description": {
            "hashtags": [
              {
                "end": 16,
                "start": 13,
                "tag": "伪娘"
              },
              {
                "end": 23,
                "start": 19,
                "tag": "跨性别"
              },
              {
                "end": 68,
                "start": 55,
                "tag": "crossdresser"
              },
              {
                "end": 72,
                "start": 69,
                "tag": "CD"
              },
              {
                "end": 82,
                "start": 78,
                "tag": "MtF"
              },
              {
                "end": 95,
                "start": 83,
                "tag": "transgender"
              },
              {
                "end": 99,
                "start": 96,
                "tag": "TS"
              },
              {
                "end": 120,
                "start": 116,
                "tag": "女装子"
              },
              {
                "end": 131,
                "start": 124,
                "tag": "ニューハーフ"
              }
            ]
          },
          "url": {
            "urls": [
              {
                "display_url": "linktr.ee/kukmoon",
                "end": 23,
                "expanded_url": "https://linktr.ee/kukmoon",
                "start": 0,
                "url": "https://t.co/RJj82hjUIU"
              }
            ]
          }
        },
        "id": "1684572167860801536",
        "location": "距离你 0.15 km",
        "name": "神楽坂谷月🏳️‍⚧️🍥",
        "pinned_tweet_id": "2058909907634810984",
        "profile_image_url": "https://pbs.twimg.com/profile_images/1907686329288437760/qxwXzNcR_normal.jpg",
        "protected": false,
        "public_metrics": {
          "followers_count": 5036,
          "following_count": 4617,
          "like_count": 95834,
          "listed_count": 4,
          "media_count": 1842,
          "tweet_count": 14496
        },
        "url": "https://t.co/RJj82hjUIU",
        "username": "kukmoon97",
        "verified": true
      }
    ]
  }
}